arch_sparring_agent/__init__.py
arch_sparring_agent/cli.py
arch_sparring_agent/config.py
arch_sparring_agent/orchestrator.py
arch_sparring_agent/agents/__init__.py
arch_sparring_agent/agents/architecture_agent.py
arch_sparring_agent/agents/ci_agents.py
arch_sparring_agent/agents/question_agent.py
arch_sparring_agent/agents/requirements_agent.py
arch_sparring_agent/agents/review_agent.py
arch_sparring_agent/agents/sparring_agent.py
arch_sparring_agent/tools/__init__.py
arch_sparring_agent/tools/cfn_analyzer.py
arch_sparring_agent/tools/diagram_analyzer.py
arch_sparring_agent/tools/document_parser.py
arch_sparring_agent/tools/source_analyzer.py
arch_sparring_agent-0.1.3.dist-info/METADATA
arch_sparring_agent-0.1.3.dist-info/WHEEL
arch_sparring_agent-0.1.3.dist-info/entry_points.txt
arch_sparring_agent-0.1.3.dist-info/licenses/LICENSE
arch_sparring_agent-0.1.3.dist-info/RECORD
