Metadata-Version: 2.4
Name: arch-sparring-agent
Version: 0.1.3
Summary: Multi-agent architecture review system using AWS Bedrock
Project-URL: Homepage, https://github.com/michelangelo17/arch-sparring-agent
Project-URL: Documentation, https://github.com/michelangelo17/arch-sparring-agent#readme
Project-URL: Repository, https://github.com/michelangelo17/arch-sparring-agent
Project-URL: Changelog, https://github.com/michelangelo17/arch-sparring-agent/blob/main/CHANGELOG.md
Project-URL: Issues, https://github.com/michelangelo17/arch-sparring-agent/issues
License: MIT
License-File: LICENSE
Keywords: agents,ai,architecture,aws,bedrock,cloudformation,review
Classifier: Development Status :: 4 - Beta
Classifier: Intended Audience :: Developers
Classifier: License :: OSI Approved :: MIT License
Classifier: Operating System :: OS Independent
Classifier: Programming Language :: Python :: 3
Classifier: Programming Language :: Python :: 3.11
Classifier: Programming Language :: Python :: 3.12
Classifier: Programming Language :: Python :: 3.13
Classifier: Programming Language :: Python :: 3.14
Classifier: Topic :: Software Development :: Quality Assurance
Classifier: Topic :: System :: Systems Administration
Requires-Python: >=3.11
Requires-Dist: bedrock-agentcore-starter-toolkit>=0.1.0
Requires-Dist: bedrock-agentcore>=1.1.1
Requires-Dist: boto3>=1.42.2
Requires-Dist: click>=8.0.0
Requires-Dist: markdown>=3.10
Requires-Dist: pillow>=12.0.0
Requires-Dist: python-frontmatter>=1.1.0
Requires-Dist: strands-agents>=1.19.0
Provides-Extra: otel
Requires-Dist: strands-agents[otel]>=1.19.0; extra == 'otel'
